<?xml version="1.0" encoding="UTF-8"?>
<list xmlns:xsi="http://www.w3.org/2001/XMLSchema-instance" xsi:noNamespaceSchemaLocation="../../xsd/skills.xsd">
	<skill id="59400" toLevel="1" name="Metal Suit Sealbook - High-grade">
		<icon>BranchSys3.icon1.g_co_sf_u</icon>
		<operateType>A1</operateType>
		<hitTime>500</hitTime>
	</skill>
	<skill id="59401" toLevel="1" name="Metal Suit Sealbook - Rare">
		<icon>BranchSys3.icon1.g_co_sf_u</icon>
		<operateType>A1</operateType>
		<hitTime>500</hitTime>
	</skill>
	<skill id="59402" toLevel="1" name="Metal Suit Sealbook - Legendary">
		<icon>BranchSys3.icon1.g_co_sf_u</icon>
		<operateType>A1</operateType>
		<hitTime>500</hitTime>
	</skill>
	<skill id="59403" toLevel="1" name="Metal Suit Sealbook - Mythic">
		<icon>BranchSys3.icon1.g_co_sf_u</icon>
		<operateType>A1</operateType>
		<hitTime>500</hitTime>
	</skill>
	<skill id="59404" toLevel="1" name="Samurai Sealbook - Standard">
		<icon>BranchSys3.iconArmar.g_co_japan_general_i00</icon>
		<operateType>A1</operateType>
		<hitTime>500</hitTime>
	</skill>
	<skill id="59405" toLevel="1" name="Samurai Sealbook - High-grade">
		<icon>BranchSys3.iconArmar.g_co_japan_general_i00</icon>
		<operateType>A1</operateType>
		<hitTime>500</hitTime>
	</skill>
	<skill id="59406" toLevel="1" name="Samurai Sealbook - Rare">
		<icon>BranchSys3.iconArmar.g_co_japan_general_i00</icon>
		<operateType>A1</operateType>
		<hitTime>500</hitTime>
	</skill>
	<skill id="59407" toLevel="1" name="Samurai Sealbook - Legendary">
		<icon>BranchSys3.iconArmar.g_co_japan_general_i00</icon>
		<operateType>A1</operateType>
		<hitTime>500</hitTime>
	</skill>
	<skill id="59408" toLevel="1" name="Samurai Sealbook - Mythic">
		<icon>BranchSys3.iconArmar.g_co_japan_general_i00</icon>
		<operateType>A1</operateType>
		<hitTime>500</hitTime>
	</skill>
	<skill id="59409" toLevel="1" name="Archer - Green Sealbook - Standard">
		<icon>BranchIcon.Icon.g_bm_costume_archer_green</icon>
		<operateType>A1</operateType>
		<hitTime>500</hitTime>
	</skill>
	<skill id="59410" toLevel="1" name="Archer - Green Sealbook - High-grade">
		<icon>BranchIcon.Icon.g_bm_costume_archer_green</icon>
		<operateType>A1</operateType>
		<hitTime>500</hitTime>
	</skill>
	<skill id="59411" toLevel="1" name="Archer - Green Sealbook - Rare">
		<icon>BranchIcon.Icon.g_bm_costume_archer_green</icon>
		<operateType>A1</operateType>
		<hitTime>500</hitTime>
	</skill>
	<skill id="59412" toLevel="1" name="Archer - Green Sealbook - Legendary">
		<icon>BranchIcon.Icon.g_bm_costume_archer_green</icon>
		<operateType>A1</operateType>
		<hitTime>500</hitTime>
	</skill>
	<skill id="59413" toLevel="1" name="Archer - Green Sealbook - Mythic">
		<icon>BranchIcon.Icon.g_bm_costume_archer_green</icon>
		<operateType>A1</operateType>
		<hitTime>500</hitTime>
	</skill>
	<skill id="59414" toLevel="1" name="Formal Wear Sealbook - Standard">
		<icon>BranchIcon.Icon.g_bm_costume_wedding</icon>
		<operateType>A1</operateType>
		<hitTime>500</hitTime>
	</skill>
	<skill id="59415" toLevel="1" name="Formal Wear Sealbook - High-grade">
		<icon>BranchIcon.Icon.g_bm_costume_wedding</icon>
		<operateType>A1</operateType>
		<hitTime>500</hitTime>
	</skill>
	<skill id="59416" toLevel="1" name="Formal Wear Sealbook - Rare">
		<icon>BranchIcon.Icon.g_bm_costume_wedding</icon>
		<operateType>A1</operateType>
		<hitTime>500</hitTime>
	</skill>
	<skill id="59417" toLevel="1" name="Formal Wear Sealbook - Legendary">
		<icon>BranchIcon.Icon.g_bm_costume_wedding</icon>
		<operateType>A1</operateType>
		<hitTime>500</hitTime>
	</skill>
	<skill id="59418" toLevel="1" name="Formal Wear Sealbook - Mythic">
		<icon>BranchIcon.Icon.g_bm_costume_wedding</icon>
		<operateType>A1</operateType>
		<hitTime>500</hitTime>
	</skill>
	<skill id="59419" toLevel="1" name="Kat the Cat Sealbook - Standard">
		<icon>icon.cat_the_cat_change_0</icon>
		<operateType>A1</operateType>
		<hitTime>500</hitTime>
	</skill>
	<skill id="59420" toLevel="1" name="Kat the Cat Sealbook - High-grade">
		<icon>icon.cat_the_cat_change_0</icon>
		<operateType>A1</operateType>
		<hitTime>500</hitTime>
	</skill>
	<skill id="59421" toLevel="1" name="Kat the Cat Sealbook - Rare">
		<icon>icon.cat_the_cat_change_0</icon>
		<operateType>A1</operateType>
		<hitTime>500</hitTime>
	</skill>
	<skill id="59422" toLevel="1" name="Kat the Cat Sealbook - Legendary">
		<icon>icon.cat_the_cat_change_0</icon>
		<operateType>A1</operateType>
		<hitTime>500</hitTime>
	</skill>
	<skill id="59423" toLevel="1" name="Kat the Cat Sealbook - Mythic">
		<icon>icon.cat_the_cat_change_0</icon>
		<operateType>A1</operateType>
		<hitTime>500</hitTime>
	</skill>
	<skill id="59424" toLevel="1" name="Halloween Sealbook - Standard">
		<icon>BranchIcon.Icon.g_bm_costume_holloween</icon>
		<operateType>A1</operateType>
		<hitTime>500</hitTime>
	</skill>
	<skill id="59425" toLevel="1" name="Halloween Sealbook - High-grade">
		<icon>BranchIcon.Icon.g_bm_costume_holloween</icon>
		<operateType>A1</operateType>
		<hitTime>500</hitTime>
	</skill>
	<skill id="59426" toLevel="1" name="Halloween Sealbook - Rare">
		<icon>BranchIcon.Icon.g_bm_costume_holloween</icon>
		<operateType>A1</operateType>
		<hitTime>500</hitTime>
	</skill>
	<skill id="59427" toLevel="1" name="Halloween Sealbook - Legendary">
		<icon>BranchIcon.Icon.g_bm_costume_holloween</icon>
		<operateType>A1</operateType>
		<hitTime>500</hitTime>
	</skill>
	<skill id="59428" toLevel="1" name="Halloween Sealbook - Mythic">
		<icon>BranchIcon.Icon.g_bm_costume_holloween</icon>
		<operateType>A1</operateType>
		<hitTime>500</hitTime>
	</skill>
	<skill id="59429" toLevel="1" name="Alluring Swimsuit Sealbook - Standard">
		<icon>BranchSys3.icon1.g_co_swimsuit_event_02</icon>
		<operateType>A1</operateType>
		<hitTime>500</hitTime>
	</skill>
	<skill id="59430" toLevel="1" name="Alluring Swimsuit Sealbook - High-grade">
		<icon>BranchSys3.icon1.g_co_swimsuit_event_02</icon>
		<operateType>A1</operateType>
		<hitTime>500</hitTime>
	</skill>
	<skill id="59431" toLevel="1" name="Alluring Swimsuit Sealbook - Rare">
		<icon>BranchSys3.icon1.g_co_swimsuit_event_02</icon>
		<operateType>A1</operateType>
		<hitTime>500</hitTime>
	</skill>
	<skill id="59432" toLevel="1" name="Alluring Swimsuit Sealbook - Legendary">
		<icon>BranchSys3.icon1.g_co_swimsuit_event_02</icon>
		<operateType>A1</operateType>
		<hitTime>500</hitTime>
	</skill>
	<skill id="59433" toLevel="1" name="Alluring Swimsuit Sealbook - Mythic">
		<icon>BranchSys3.icon1.g_co_swimsuit_event_02</icon>
		<operateType>A1</operateType>
		<hitTime>500</hitTime>
	</skill>
	<skill id="59434" toLevel="1" name="Vampiric Sealbook - Standard">
		<icon>BranchSys3.iconArmar.g_co_vampiric_u_i00</icon>
		<operateType>A1</operateType>
		<hitTime>500</hitTime>
	</skill>
	<skill id="59435" toLevel="1" name="Vampiric Sealbook - High-grade">
		<icon>BranchSys3.iconArmar.g_co_vampiric_u_i00</icon>
		<operateType>A1</operateType>
		<hitTime>500</hitTime>
	</skill>
	<skill id="59436" toLevel="1" name="Vampiric Sealbook - Rare">
		<icon>BranchSys3.iconArmar.g_co_vampiric_u_i00</icon>
		<operateType>A1</operateType>
		<hitTime>500</hitTime>
	</skill>
	<skill id="59437" toLevel="1" name="Vampiric Sealbook - Legendary">
		<icon>BranchSys3.iconArmar.g_co_vampiric_u_i00</icon>
		<operateType>A1</operateType>
		<hitTime>500</hitTime>
	</skill>
	<skill id="59438" toLevel="1" name="Vampiric Sealbook - Mythic">
		<icon>BranchSys3.iconArmar.g_co_vampiric_u_i00</icon>
		<operateType>A1</operateType>
		<hitTime>500</hitTime>
	</skill>
	<skill id="59439" toLevel="1" name="Dark Knight Sealbook - Standard">
		<icon>icon.dark_kninght</icon>
		<operateType>A1</operateType>
		<hitTime>500</hitTime>
	</skill>
	<skill id="59440" toLevel="1" name="Dark Knight Sealbook - High-grade">
		<icon>icon.dark_kninght</icon>
		<operateType>A1</operateType>
		<hitTime>500</hitTime>
	</skill>
	<skill id="59441" toLevel="1" name="Dark Knight Sealbook - Rare">
		<icon>icon.dark_kninght</icon>
		<operateType>A1</operateType>
		<hitTime>500</hitTime>
	</skill>
	<skill id="59442" toLevel="1" name="Dark Knight Sealbook - Legendary">
		<icon>icon.dark_kninght</icon>
		<operateType>A1</operateType>
		<hitTime>500</hitTime>
	</skill>
	<skill id="59443" toLevel="1" name="Dark Knight Sealbook - Mythic">
		<icon>icon.dark_kninght</icon>
		<operateType>A1</operateType>
		<hitTime>500</hitTime>
	</skill>
	<skill id="59444" toLevel="1" name="Chevalier Sealbook - Standard">
		<icon>icon.chevalier_chest_change</icon>
		<operateType>A1</operateType>
		<hitTime>500</hitTime>
	</skill>
	<skill id="59445" toLevel="1" name="Chevalier Sealbook - High-grade">
		<icon>icon.chevalier_chest_change</icon>
		<operateType>A1</operateType>
		<hitTime>500</hitTime>
	</skill>
	<skill id="59446" toLevel="1" name="Chevalier Sealbook - Rare">
		<icon>icon.chevalier_chest_change</icon>
		<operateType>A1</operateType>
		<hitTime>500</hitTime>
	</skill>
	<skill id="59447" toLevel="1" name="Chevalier Sealbook - Legendary">
		<icon>icon.chevalier_chest_change</icon>
		<operateType>A1</operateType>
		<hitTime>500</hitTime>
	</skill>
	<skill id="59448" toLevel="1" name="Chevalier Sealbook - Mythic">
		<icon>icon.chevalier_chest_change</icon>
		<operateType>A1</operateType>
		<hitTime>500</hitTime>
	</skill>
	<skill id="59449" toLevel="1" name="Archer - Red Sealbook - Standard">
		<icon>BranchIcon.Icon.g_bm_costume_archer_red</icon>
		<operateType>A1</operateType>
		<hitTime>500</hitTime>
	</skill>
	<skill id="59450" toLevel="1" name="Archer - Red Sealbook - High-grade">
		<icon>BranchIcon.Icon.g_bm_costume_archer_red</icon>
		<operateType>A1</operateType>
		<hitTime>500</hitTime>
	</skill>
	<skill id="59451" toLevel="1" name="Archer - Red Sealbook - Rare">
		<icon>BranchIcon.Icon.g_bm_costume_archer_red</icon>
		<operateType>A1</operateType>
		<hitTime>500</hitTime>
	</skill>
	<skill id="59452" toLevel="1" name="Archer - Red Sealbook - Legendary">
		<icon>BranchIcon.Icon.g_bm_costume_archer_red</icon>
		<operateType>A1</operateType>
		<hitTime>500</hitTime>
	</skill>
	<skill id="59453" toLevel="1" name="Archer - Red Sealbook - Mythic">
		<icon>BranchIcon.Icon.g_bm_costume_archer_red</icon>
		<operateType>A1</operateType>
		<hitTime>500</hitTime>
	</skill>
	<skill id="59454" toLevel="1" name="Pirate - Blue Sealbook - Standard">
		<icon>BranchIcon.Icon.g_bm_costume_pirate_blue</icon>
		<operateType>A1</operateType>
		<hitTime>500</hitTime>
	</skill>
	<skill id="59455" toLevel="1" name="Pirate - Blue Sealbook - High-grade">
		<icon>BranchIcon.Icon.g_bm_costume_pirate_blue</icon>
		<operateType>A1</operateType>
		<hitTime>500</hitTime>
	</skill>
	<skill id="59456" toLevel="1" name="Pirate - Blue Sealbook - Rare">
		<icon>BranchIcon.Icon.g_bm_costume_pirate_blue</icon>
		<operateType>A1</operateType>
		<hitTime>500</hitTime>
	</skill>
	<skill id="59457" toLevel="1" name="Pirate - Blue Sealbook - Legendary">
		<icon>BranchIcon.Icon.g_bm_costume_pirate_blue</icon>
		<operateType>A1</operateType>
		<hitTime>500</hitTime>
	</skill>
	<skill id="59458" toLevel="1" name="Pirate - Blue Sealbook - Mythic">
		<icon>BranchIcon.Icon.g_bm_costume_pirate_blue</icon>
		<operateType>A1</operateType>
		<hitTime>500</hitTime>
	</skill>
	<skill id="59459" toLevel="1" name="Wizard - Wine Sealbook - Standard">
		<icon>BranchIcon.Icon.g_bm_costume_wizard_wine</icon>
		<operateType>A1</operateType>
		<hitTime>500</hitTime>
	</skill>
	<skill id="59460" toLevel="1" name="Wizard - Wine Sealbook - High-grade">
		<icon>BranchIcon.Icon.g_bm_costume_wizard_wine</icon>
		<operateType>A1</operateType>
		<hitTime>500</hitTime>
	</skill>
	<skill id="59461" toLevel="1" name="Wizard - Wine Sealbook - Rare">
		<icon>BranchIcon.Icon.g_bm_costume_wizard_wine</icon>
		<operateType>A1</operateType>
		<hitTime>500</hitTime>
	</skill>
	<skill id="59462" toLevel="1" name="Wizard - Wine Sealbook - Legendary">
		<icon>BranchIcon.Icon.g_bm_costume_wizard_wine</icon>
		<operateType>A1</operateType>
		<hitTime>500</hitTime>
	</skill>
	<skill id="59463" toLevel="1" name="Wizard - Wine Sealbook - Mythic">
		<icon>BranchIcon.Icon.g_bm_costume_wizard_wine</icon>
		<operateType>A1</operateType>
		<hitTime>500</hitTime>
	</skill>
	<skill id="59464" toLevel="1" name="Magician Sealbook - Standard">
		<icon>BranchIcon.Icon.g_bm_costume_magician</icon>
		<operateType>A1</operateType>
		<hitTime>500</hitTime>
	</skill>
	<skill id="59465" toLevel="1" name="Magician Sealbook - High-grade">
		<icon>BranchIcon.Icon.g_bm_costume_magician</icon>
		<operateType>A1</operateType>
		<hitTime>500</hitTime>
	</skill>
	<skill id="59466" toLevel="1" name="Magician Sealbook - Rare">
		<icon>BranchIcon.Icon.g_bm_costume_magician</icon>
		<operateType>A1</operateType>
		<hitTime>500</hitTime>
	</skill>
	<skill id="59467" toLevel="1" name="Magician Sealbook - Legendary">
		<icon>BranchIcon.Icon.g_bm_costume_magician</icon>
		<operateType>A1</operateType>
		<hitTime>500</hitTime>
	</skill>
	<skill id="59468" toLevel="1" name="Magician Sealbook - Mythic">
		<icon>BranchIcon.Icon.g_bm_costume_magician</icon>
		<operateType>A1</operateType>
		<hitTime>500</hitTime>
	</skill>
	<skill id="59469" toLevel="1" name="Sailor Sealbook - Standard">
		<icon>icon.bm2018_pirate_i01</icon>
		<operateType>A1</operateType>
		<hitTime>500</hitTime>
	</skill>
	<skill id="59470" toLevel="1" name="Sailor Sealbook - High-grade">
		<icon>icon.bm2018_pirate_i01</icon>
		<operateType>A1</operateType>
		<hitTime>500</hitTime>
	</skill>
	<skill id="59471" toLevel="1" name="Sailor Sealbook - Rare">
		<icon>icon.bm2018_pirate_i01</icon>
		<operateType>A1</operateType>
		<hitTime>500</hitTime>
	</skill>
	<skill id="59472" toLevel="1" name="Sailor Sealbook - Legendary">
		<icon>icon.bm2018_pirate_i01</icon>
		<operateType>A1</operateType>
		<hitTime>500</hitTime>
	</skill>
	<skill id="59473" toLevel="1" name="Sailor Sealbook - Mythic">
		<icon>icon.bm2018_pirate_i01</icon>
		<operateType>A1</operateType>
		<hitTime>500</hitTime>
	</skill>
	<skill id="59474" toLevel="1" name="Noblesse - Red Sealbook - Standard">
		<icon>icon.bm2018_rednoblesse_i01</icon>
		<operateType>A1</operateType>
		<hitTime>500</hitTime>
	</skill>
	<skill id="59475" toLevel="1" name="Noblesse - Red Sealbook - High-grade">
		<icon>icon.bm2018_rednoblesse_i01</icon>
		<operateType>A1</operateType>
		<hitTime>500</hitTime>
	</skill>
	<skill id="59476" toLevel="1" name="Noblesse - Red Sealbook - Rare">
		<icon>icon.bm2018_rednoblesse_i01</icon>
		<operateType>A1</operateType>
		<hitTime>500</hitTime>
	</skill>
	<skill id="59477" toLevel="1" name="Noblesse - Red Sealbook - Legendary">
		<icon>icon.bm2018_rednoblesse_i01</icon>
		<operateType>A1</operateType>
		<hitTime>500</hitTime>
	</skill>
	<skill id="59478" toLevel="1" name="Noblesse - Red Sealbook - Mythic">
		<icon>icon.bm2018_rednoblesse_i01</icon>
		<operateType>A1</operateType>
		<hitTime>500</hitTime>
	</skill>
	<skill id="59479" toLevel="1" name="Barbarian Wolf Sealbook - Standard">
		<icon>icon.barbarian_chest_change_0</icon>
		<operateType>A1</operateType>
		<hitTime>500</hitTime>
	</skill>
	<skill id="59480" toLevel="1" name="Barbarian Wolf Sealbook - High-grade">
		<icon>icon.barbarian_chest_change_0</icon>
		<operateType>A1</operateType>
		<hitTime>500</hitTime>
	</skill>
	<skill id="59481" toLevel="1" name="Barbarian Wolf Sealbook - Rare">
		<icon>icon.barbarian_chest_change_0</icon>
		<operateType>A1</operateType>
		<hitTime>500</hitTime>
	</skill>
	<skill id="59482" toLevel="1" name="Barbarian Wolf Sealbook - Legendary">
		<icon>icon.barbarian_chest_change_0</icon>
		<operateType>A1</operateType>
		<hitTime>500</hitTime>
	</skill>
	<skill id="59483" toLevel="1" name="Barbarian Wolf Sealbook - Mythic">
		<icon>icon.barbarian_chest_change_0</icon>
		<operateType>A1</operateType>
		<hitTime>500</hitTime>
	</skill>
	<skill id="59484" toLevel="1" name="Valkyrie Sealbook - Standard">
		<icon>icon.valkyrie_chest_change_0</icon>
		<operateType>A1</operateType>
		<hitTime>500</hitTime>
	</skill>
	<skill id="59485" toLevel="1" name="Valkyrie Sealbook - High-grade">
		<icon>icon.valkyrie_chest_change_0</icon>
		<operateType>A1</operateType>
		<hitTime>500</hitTime>
	</skill>
	<skill id="59486" toLevel="1" name="Valkyrie Sealbook - Rare">
		<icon>icon.valkyrie_chest_change_0</icon>
		<operateType>A1</operateType>
		<hitTime>500</hitTime>
	</skill>
	<skill id="59487" toLevel="1" name="Valkyrie Sealbook - Legendary">
		<icon>icon.valkyrie_chest_change_0</icon>
		<operateType>A1</operateType>
		<hitTime>500</hitTime>
	</skill>
	<skill id="59488" toLevel="1" name="Valkyrie Sealbook - Mythic">
		<icon>icon.valkyrie_chest_change_0</icon>
		<operateType>A1</operateType>
		<hitTime>500</hitTime>
	</skill>
	<skill id="59489" toLevel="1" name="Kelbim Sealbook - Standard">
		<icon>BranchIcon.Icon.g_bm_costume_kelbim</icon>
		<operateType>A1</operateType>
		<hitTime>500</hitTime>
	</skill>
	<skill id="59490" toLevel="1" name="Kelbim Sealbook - High-grade">
		<icon>BranchIcon.Icon.g_bm_costume_kelbim</icon>
		<operateType>A1</operateType>
		<hitTime>500</hitTime>
	</skill>
	<skill id="59491" toLevel="1" name="Kelbim Sealbook - Rare">
		<icon>BranchIcon.Icon.g_bm_costume_kelbim</icon>
		<operateType>A1</operateType>
		<hitTime>500</hitTime>
	</skill>
	<skill id="59492" toLevel="1" name="Kelbim Sealbook - Legendary">
		<icon>BranchIcon.Icon.g_bm_costume_kelbim</icon>
		<operateType>A1</operateType>
		<hitTime>500</hitTime>
	</skill>
	<skill id="59493" toLevel="1" name="Kelbim Sealbook - Mythic">
		<icon>BranchIcon.Icon.g_bm_costume_kelbim</icon>
		<operateType>A1</operateType>
		<hitTime>500</hitTime>
	</skill>
	<skill id="59494" toLevel="1" name="Ninja Sealbook - Standard">
		<icon>icon.bm2018_ninja_i01</icon>
		<operateType>A1</operateType>
		<hitTime>500</hitTime>
	</skill>
	<skill id="59495" toLevel="1" name="Ninja Sealbook - High-grade">
		<icon>icon.bm2018_ninja_i01</icon>
		<operateType>A1</operateType>
		<hitTime>500</hitTime>
	</skill>
	<skill id="59496" toLevel="1" name="Ninja Sealbook - Rare">
		<icon>icon.bm2018_ninja_i01</icon>
		<operateType>A1</operateType>
		<hitTime>500</hitTime>
	</skill>
	<skill id="59497" toLevel="1" name="Ninja Sealbook - Legendary">
		<icon>icon.bm2018_ninja_i01</icon>
		<operateType>A1</operateType>
		<hitTime>500</hitTime>
	</skill>
	<skill id="59498" toLevel="1" name="Ninja Sealbook - Mythic">
		<icon>icon.bm2018_ninja_i01</icon>
		<operateType>A1</operateType>
		<hitTime>500</hitTime>
	</skill>
	<skill id="59499" toLevel="1" name="High Priest Sealbook - Standard">
		<icon>icon.bm2018_healer_i01</icon>
		<operateType>A1</operateType>
		<hitTime>500</hitTime>
	</skill>
</list>
