<?xml version="1.0" encoding="UTF-8"?>
<list xmlns:xsi="http://www.w3.org/2001/XMLSchema-instance" xsi:noNamespaceSchemaLocation="../../xsd/skills.xsd">
	<skill id="52001" toLevel="1" name="Flag Display">
		<!-- In order to get recognition, display the combat flag on the fortress' flagpole. -->
		<icon>icon.weapon_fort_flag_i00</icon>
		<castRange>85</castRange>
		<effectRange>400</effectRange>
		<hitTime>15000</hitTime>
		<isMagic>4</isMagic>
		<magicLevel>85</magicLevel>
		<operateType>A1</operateType>
		<mpConsume>50</mpConsume>
		<reuseDelay>5000</reuseDelay>
		<staticReuse>true</staticReuse>
		<magicCriticalRate>5</magicCriticalRate>
		<targetType>TARGET</targetType>
		<affectScope>SINGLE</affectScope>
		<conditions>
			<condition name="CanTakeFort" />
		</conditions>
		<startEffects>
			<effect name="TakeFortStart" />
		</startEffects>
		<effects>
			<effect name="TakeFort">
				<chance>100</chance>
			</effect>
		</effects>
	</skill>
	<skill id="52002" toLevel="1" name="Flag Power - Warrior">
		<!-- Flag Power for warriors. Decreases nearby enemies' Speed. -->
		<icon>icon.skill1298</icon>
		<operateType>P</operateType>
		<abnormalVisualEffect>FORT_FLAG_AVE</abnormalVisualEffect>
		<effects>
			<effect name="Speed">
				<amount>-50</amount>
				<mode>PER</mode>
			</effect>
		</effects>
	</skill>
	<skill id="52003" toLevel="1" name="Flag Power - Knight">
		<!-- Flag Power for knights. Increases P./ M. Def. and Debuff Resistance. -->
		<icon>icon.skill0110</icon>
		<abnormalLevel>
			<value level="1">1</value>
		</abnormalLevel>
		<abnormalTime>30</abnormalTime>
		<abnormalType>PD_UP_SPECIAL</abnormalType>
		<abnormalVisualEffect>ULTIMATE_DEFENCE</abnormalVisualEffect>
		<operateType>A2</operateType>
		<hitTime>1500</hitTime>
		<reuseDelay>60000</reuseDelay>
		<basicProperty>NONE</basicProperty>
		<magicCriticalRate>5</magicCriticalRate>
		<targetType>SELF</targetType>
		<affectScope>SINGLE</affectScope>
		<effects>
			<effect name="MagicalDefence">
				<amount>
					<value level="1">1620</value>
					<value level="2">3240</value>
				</amount>
				<mode>DIFF</mode>
			</effect>
			<effect name="PhysicalDefence">
				<amount>
					<value level="1">1800</value>
					<value level="2">3600</value>
				</amount>
				<mode>DIFF</mode>
			</effect>
			<effect name="ResistDispelByCategory">
				<amount>-80</amount>
				<slot>BUFF</slot>
			</effect>
		</effects>
	</skill>
	<skill id="52004" toLevel="1" name="Flag Power - Rogue">
		<!-- Flag Power for rogues. Increases P. Evasion и P. Skill Evasion. -->
		<icon>icon.skill0111</icon>
		<operateType>A2</operateType>
		<coolTime>500</coolTime>
		<abnormalLevel>1</abnormalLevel>
		<abnormalTime>120</abnormalTime>
		<abnormalType>PUBLIC_SLOT</abnormalType>
		<isMagic>1</isMagic>
		<operateType>A2</operateType>
		<hitTime>1500</hitTime>
		<reuseDelay>60000</reuseDelay>
		<basicProperty>NONE</basicProperty>
		<magicCriticalRate>-5</magicCriticalRate>
		<specialLevel>-1</specialLevel>
		<targetType>SELF</targetType>
		<affectScope>SINGLE</affectScope>
		<effects>
			<effect name="PhysicalEvasion">
				<amount>30</amount>
				<mode>DIFF</mode>
			</effect>
		</effects>
	</skill>
	<skill id="52005" toLevel="1" name="Flag Power - Archer">
		<!-- Flag Power for archers. Increases P. Evasion и P. Skill Evasion. -->
		<icon>icon.skill0111</icon>
		<operateType>A2</operateType>
		<coolTime>500</coolTime>
		<abnormalLevel>1</abnormalLevel>
		<abnormalTime>120</abnormalTime>
		<abnormalType>PUBLIC_SLOT</abnormalType>
		<isMagic>1</isMagic>
		<operateType>A2</operateType>
		<hitTime>1500</hitTime>
		<reuseDelay>60000</reuseDelay>
		<basicProperty>NONE</basicProperty>
		<magicCriticalRate>-5</magicCriticalRate>
		<specialLevel>-1</specialLevel>
		<targetType>SELF</targetType>
		<affectScope>SINGLE</affectScope>
		<effects>
			<effect name="PhysicalEvasion">
				<amount>30</amount>
				<mode>DIFF</mode>
			</effect>
		</effects>
	</skill>
	<skill id="52006" toLevel="1" name="Flag Power - Mage">
		<!-- Flag power for mages. Inflicts Sleep on nearby enemies. -->
		<icon>icon.skill1072</icon>
		<operateType>A2</operateType>
		<coolTime>500</coolTime>
		<abnormalLevel>1</abnormalLevel>
		<abnormalTime>5</abnormalTime>
		<abnormalType>SLEEP</abnormalType>
		<abnormalVisualEffect>SLEEP</abnormalVisualEffect>
		<activateRate>70</activateRate>
		<affectLimit>9-10</affectLimit>
		<affectRange>200</affectRange>
		<basicProperty>MAGIC</basicProperty>
		<castRange>600</castRange>
		<effectPoint>
			<value level="1">-418</value>
		</effectPoint>
		<effectRange>1200</effectRange>
		<hitTime>1500</hitTime>
		<reuseDelay>10000</reuseDelay>
		<isDebuff>true</isDebuff>
		<isMagic>1</isMagic>
		<mpConsume>
			<value level="1">59</value>
		</mpConsume>
		<removedOnDamage>true</removedOnDamage>
		<magicCriticalRate>5</magicCriticalRate>
		<trait>SLEEP</trait>
		<targetType>ENEMY_ONLY</targetType>
		<affectScope>RANGE</affectScope>
		<affectObject>NOT_FRIEND</affectObject>
		<effects>
			<effect name="BlockActions">
				<allowedSkills>35016;35045;18103</allowedSkills>
			</effect>
		</effects>
	</skill>
	<skill id="52007" toLevel="1" name="Flag Power - Summoner">
		<!-- Flag power for summoners. Inflicts Stun on nearby enemies. -->
		<icon>icon.skill0048</icon>
		<operateType>A2</operateType>
		<coolTime>500</coolTime>
		<abnormalLevel>1</abnormalLevel>
		<abnormalTime>3</abnormalTime>
		<abnormalType>STUN</abnormalType>
		<abnormalVisualEffect>STUN</abnormalVisualEffect>
		<activateRate>50</activateRate>
		<affectLimit>6-12</affectLimit>
		<affectRange>150</affectRange>
		<basicProperty>PHYSICAL</basicProperty>
		<coolTime>720</coolTime>
		<effectPoint>
			<value level="1">-590</value>
		</effectPoint>
		<isDebuff>true</isDebuff>
		<lvlBonusRate>20</lvlBonusRate>
		<mpConsume>
			<value level="1">59</value>
		</mpConsume>
		<hitTime>1500</hitTime>
		<reuseDelay>10000</reuseDelay>
		<reuseDelayGroup>48</reuseDelayGroup>
		<magicCriticalRate>5</magicCriticalRate>
		<trait>SHOCK</trait>
		<targetType>ENEMY_ONLY</targetType>
		<affectScope>RANGE</affectScope>
		<affectObject>NOT_FRIEND</affectObject>
		<effects>
			<effect name="BlockActions">
				<allowedSkills>35016;35045;18103</allowedSkills>
			</effect>
		</effects>
	</skill>
	<skill id="52008" toLevel="1" name="Flag Power - Healer">
		<!-- Flag power for healers. Inflicts Sleep on nearby enemies. -->
		<icon>icon.skill1072</icon>
		<operateType>A2</operateType>
		<coolTime>500</coolTime>
		<abnormalLevel>1</abnormalLevel>
		<abnormalTime>5</abnormalTime>
		<abnormalType>SLEEP</abnormalType>
		<abnormalVisualEffect>SLEEP</abnormalVisualEffect>
		<activateRate>70</activateRate>
		<affectLimit>9-10</affectLimit>
		<affectRange>200</affectRange>
		<basicProperty>MAGIC</basicProperty>
		<castRange>600</castRange>
		<effectPoint>
			<value level="1">-418</value>
		</effectPoint>
		<effectRange>1200</effectRange>
		<isDebuff>true</isDebuff>
		<isMagic>1</isMagic>
		<mpConsume>
			<value level="1">59</value>
		</mpConsume>
		<removedOnDamage>true</removedOnDamage>
		<hitTime>1500</hitTime>
		<reuseDelay>10000</reuseDelay>
		<magicCriticalRate>5</magicCriticalRate>
		<trait>SLEEP</trait>
		<targetType>ENEMY_ONLY</targetType>
		<affectScope>RANGE</affectScope>
		<affectObject>NOT_FRIEND</affectObject>
		<effects>
			<effect name="BlockActions">
				<allowedSkills>35016;35045;18103</allowedSkills>
			</effect>
		</effects>
	</skill>
	<skill id="52009" toLevel="1" name="Flag Power - Enchanter">
		<!-- Flag power for enchanters. Inflicts Hold on nearby enemies. -->
		<icon>icon.skill1201</icon>
		<coolTime>500</coolTime>
		<abnormalLevel>1</abnormalLevel>
		<abnormalTime>
			<value level="1">30</value>
		</abnormalTime>
		<abnormalType>ROOT_MAGICALLY</abnormalType>
		<abnormalVisualEffect>ROOT</abnormalVisualEffect>
		<activateRate>70</activateRate>
		<basicProperty>MAGIC</basicProperty>
		<castRange>750</castRange>
		<effectPoint>-100</effectPoint>
		<effectRange>1250</effectRange>
		<hitTime>1500</hitTime>
		<reuseDelay>20000</reuseDelay>
		<isDebuff>true</isDebuff>
		<mpConsume>
			<value level="1">53</value>
		</mpConsume>
		<operateType>A2</operateType>
		<magicCriticalRate>-5</magicCriticalRate>
		<trait>HOLD</trait>
		<targetType>ENEMY_ONLY</targetType>
		<affectScope>RANGE</affectScope>
		<affectObject>NOT_FRIEND</affectObject>
		<effects>
			<effect name="Root" />
		</effects>
	</skill>
	<skill id="52010" toLevel="1" name="Flag Power - Bard">
		<!-- Flag power for bards. Inflicts Stun on nearby enemies. -->
		<icon>icon.skill0048</icon>
		<operateType>A2</operateType>
		<coolTime>500</coolTime>
		<abnormalLevel>1</abnormalLevel>
		<abnormalTime>3</abnormalTime>
		<abnormalType>STUN</abnormalType>
		<abnormalVisualEffect>STUN</abnormalVisualEffect>
		<activateRate>50</activateRate>
		<affectLimit>6-12</affectLimit>
		<affectRange>150</affectRange>
		<basicProperty>PHYSICAL</basicProperty>
		<coolTime>720</coolTime>
		<effectPoint>
			<value level="1">-590</value>
		</effectPoint>
		<isDebuff>true</isDebuff>
		<lvlBonusRate>20</lvlBonusRate>
		<mpConsume>
			<value level="1">59</value>
		</mpConsume>
		<hitTime>1500</hitTime>
		<reuseDelay>10000</reuseDelay>
		<reuseDelayGroup>48</reuseDelayGroup>
		<magicCriticalRate>5</magicCriticalRate>
		<trait>SHOCK</trait>
		<targetType>ENEMY_ONLY</targetType>
		<affectScope>RANGE</affectScope>
		<affectObject>NOT_FRIEND</affectObject>
		<effects>
			<effect name="BlockActions">
				<allowedSkills>35016;35045;18103</allowedSkills>
			</effect>
		</effects>
	</skill>
	<skill id="52011" toLevel="1" name="Flag Power - Shaman">
		<!-- Flag power for shamans. Inflicts Fear on nearby enemies. -->
		<icon>icon.skill1092</icon>
		<coolTime>500</coolTime>
		<abnormalLevel>1</abnormalLevel>
		<abnormalTime>3</abnormalTime>
		<abnormalType>TURN_FLEE</abnormalType>
		<abnormalVisualEffect>TURN_FLEE</abnormalVisualEffect>
		<activateRate>40</activateRate>
		<basicProperty>MAGIC</basicProperty>
		<castRange>600</castRange>
		<effectPoint>
			<value level="1">-162</value>
		</effectPoint>
		<effectRange>1200</effectRange>
		<isDebuff>true</isDebuff>
		<isMagic>1</isMagic>
		<lvlBonusRate>20</lvlBonusRate>
		<mpConsume>
			<value level="1">54</value>
		</mpConsume>
		<operateType>A2</operateType>
		<hitTime>1500</hitTime>
		<reuseDelay>10000</reuseDelay>
		<magicCriticalRate>5</magicCriticalRate>
		<trait>DERANGEMENT</trait>
		<targetType>ENEMY_ONLY</targetType>
		<affectScope>RANGE</affectScope>
		<affectObject>NOT_FRIEND</affectObject>
		<effects>
			<effect name="BlockControl" />
			<effect name="Fear" />
		</effects>
	</skill>
	<skill id="52012" toLevel="1" name="Flag Power - Fast Run">
		<!-- Flag Power temporarily increases Speed. -->
		<icon>icon.skill0004</icon>
		<operateType>A2</operateType>
		<coolTime>500</coolTime>
		<hitTime>1000</hitTime>
		<reuseDelay>20000</reuseDelay>
		<staticReuse>true</staticReuse>
		<abnormalTime>20</abnormalTime>
		<basicProperty>NONE</basicProperty>
		<magicCriticalRate>5</magicCriticalRate>
		<targetType>SELF</targetType>
		<affectScope>SINGLE</affectScope>
		<effects>
			<effect name="Speed">
				<amount>30</amount>
				<mode>DIFF</mode>
			</effect>
		</effects>
	</skill>
	<skill id="52013" toLevel="1" name="Flag Equip">
		<!-- Speed of the flag bearer is decreased. -->
		<icon>icon.weapon_fort_flag_i00</icon>
		<operateType>P</operateType>
		<abnormalVisualEffect>FORT_FLAG_AVE</abnormalVisualEffect>
		<effects>
			<effect name="Speed">
				<amount>-50</amount>
				<mode>PER</mode>
			</effect>
		</effects>
	</skill>
	<skill id="52014" toLevel="1" name="Get Combat Flag">
		<!-- You have got the power of Combat Flag. -->
		<icon>icon.weapon_fort_flag_i00</icon>
		<operateType>A1</operateType>
	</skill>
	<skill id="52015" toLevel="1" name="Drop Combat Flag">
		<!-- You have lost the power of Combat Flag. -->
		<icon>icon.weapon_fort_flag_i00</icon>
		<operateType>A1</operateType>
	</skill>
	<skill id="52016" toLevel="1" name="Orc Fortress Siege">
		<!-- A special ability given to the clan members who own the Orc Fortress. Acquired XP/ SP +30%, gained adena +20%. -->
		<icon>icon.skill32121</icon>
		<operateType>P</operateType>
		<magicCriticalRate>5</magicCriticalRate>
		<magicLevel>1</magicLevel>
		<effects>
			<effect name="ExpModify">
				<amount>
					<value level="1">10</value>
				</amount>
			</effect>
			<effect name="SpModify">
				<amount>
					<value level="1">10</value>
				</amount>
			</effect>
		</effects>
	</skill>
	<skill id="52017" toLevel="1" name="Remote Flag Display">
		<!-- In order to get recognition, display the combat flag on the fortress' flagpole. There's a chance to fail. -->
		<icon>icon.weapon_fort_flag_i00</icon>
		<castRange>1100</castRange>
		<effectRange>1800</effectRange>
		<hitTime>15000</hitTime>
		<isMagic>4</isMagic>
		<magicLevel>85</magicLevel>
		<operateType>A1</operateType>
		<mpConsume>50</mpConsume>
		<reuseDelay>5000</reuseDelay>
		<staticReuse>true</staticReuse>
		<magicCriticalRate>5</magicCriticalRate>
		<targetType>TARGET</targetType>
		<affectScope>SINGLE</affectScope>
		<conditions>
			<condition name="CanTakeFort" />
		</conditions>
		<startEffects>
			<effect name="TakeFortStart" />
		</startEffects>
		<effects>
			<effect name="TakeFort">
				<chance>100</chance>
			</effect>
		</effects>
	</skill>
	<skill id="52018" toLevel="1" name="Leader Power">
		<!-- STR +1. INT +1. P. Evasion +20. HP Recovery Potions' Effect +10 -->
		<icon>icon.1st_ranking_share_buff</icon>
		<abnormalTime>14600</abnormalTime>
		<stayAfterDeath>true</stayAfterDeath>
		<castRange>300</castRange>
		<effectRange>315</effectRange>
		<isMagic>2</isMagic>
		<operateType>A2</operateType>
		<targetType>SELF</targetType>
		<affectScope>SINGLE</affectScope>
		<effects>
			<effect name="StatUp">
				<amount>1</amount>
				<stat>STR</stat>
			</effect>
			<effect name="StatUp">
				<amount>1</amount>
				<stat>INT</stat>
			</effect>
			<effect name="PhysicalEvasion">
				<amount>20</amount>
				<mode>DIFF</mode>
			</effect>
			<effect name="SkillEvasion">
				<magicType>0</magicType>
				<amount>20</amount>
			</effect>
			<effect name="AdditionalPotionHp">
				<amount>10</amount>
				<mode>DIFF</mode>
			</effect>
		</effects>
	</skill>
	<skill id="52019" toLevel="1" name="PvP Ranking">
		<!-- Bonus for the 1st-3rd places in PvP Ranking. When you have killed, you can see a special visual effect for a short period of time. -->
		<icon>icon.pvp_ranking</icon>
		<magicLevel>40</magicLevel>
		<operateType>A2</operateType>
		<abnormalLevel>1</abnormalLevel>
		<abnormalTime>-1</abnormalTime>
		<magicCriticalRate>5</magicCriticalRate>
		<isTriggeredSkill>true</isTriggeredSkill>
		<irreplacableBuff>true</irreplacableBuff>
		<canBeDispelled>false</canBeDispelled>
		<stayAfterDeath>true</stayAfterDeath>
		<isMagic>4</isMagic>
		<targetType>SELF</targetType>
		<affectScope>SINGLE</affectScope>
	</skill>
	<skill id="52020" toLevel="1" name="PvP Ranking Effect">
		<icon>icon.skill0000</icon>
		<operateType>A1</operateType>
	</skill>
</list>
